rgtfs/__init__.py
rgtfs/entrypoint.py
rgtfs/helpers/__init__.py
rgtfs/helpers/treat_rj_brt_realized_trips.py
rgtfs/io.py
rgtfs/simple.py
rgtfs/tables.py
rgtfs/utils.py
rgtfs-0.1.0.dist-info/LICENSE
rgtfs-0.1.0.dist-info/WHEEL
rgtfs-0.1.0.dist-info/METADATA
rgtfs-0.1.0.dist-info/RECORD
