Metadata-Version: 2.1
Name: rgtfs
Version: 0.1.0
Summary: Calculates the retroactive GTFS based on GPS data
Home-page: https://github.com/RJ-SMTR/rGTFS
License: MIT
Author: Joao Carabetta
Author-email: joao.carabetta@gmail.com
Requires-Python: >=3.6,<4.0
Classifier: License :: OSI Approved :: MIT License
Classifier: Programming Language :: Python :: 3
Classifier: Programming Language :: Python :: 3.6
Classifier: Programming Language :: Python :: 3.7
Classifier: Programming Language :: Python :: 3.8
Classifier: Programming Language :: Python :: 3.9
Classifier: Topic :: Software Development :: Build Tools
Classifier: Topic :: Software Development :: Libraries :: Python Modules
Requires-Dist: gtfs-kit (==5.0.2)
Requires-Dist: pandas (>=1.1.0,<2.0.0)
Requires-Dist: pymove (==2.7.2)
Project-URL: Repository, https://github.com/RJ-SMTR/rGTFS
